kalshi_python_async/__init__.py
kalshi_python_async/api_client.py
kalshi_python_async/api_response.py
kalshi_python_async/auth.py
kalshi_python_async/configuration.py
kalshi_python_async/exceptions.py
kalshi_python_async/py.typed
kalshi_python_async/rest.py
kalshi_python_async/api/__init__.py
kalshi_python_async/api/api_keys_api.py
kalshi_python_async/api/communications_api.py
kalshi_python_async/api/events_api.py
kalshi_python_async/api/exchange_api.py
kalshi_python_async/api/fcm_api.py
kalshi_python_async/api/incentive_programs_api.py
kalshi_python_async/api/live_data_api.py
kalshi_python_async/api/market_api.py
kalshi_python_async/api/milestone_api.py
kalshi_python_async/api/multivariate_api.py
kalshi_python_async/api/order_groups_api.py
kalshi_python_async/api/orders_api.py
kalshi_python_async/api/portfolio_api.py
kalshi_python_async/api/search_api.py
kalshi_python_async/api/structured_targets_api.py
kalshi_python_async/models/__init__.py
kalshi_python_async/models/accept_quote_request.py
kalshi_python_async/models/amend_order_request.py
kalshi_python_async/models/amend_order_response.py
kalshi_python_async/models/announcement.py
kalshi_python_async/models/api_key.py
kalshi_python_async/models/associated_event.py
kalshi_python_async/models/batch_cancel_orders_individual_response.py
kalshi_python_async/models/batch_cancel_orders_request.py
kalshi_python_async/models/batch_cancel_orders_response.py
kalshi_python_async/models/batch_create_orders_individual_response.py
kalshi_python_async/models/batch_create_orders_request.py
kalshi_python_async/models/batch_create_orders_response.py
kalshi_python_async/models/batch_get_market_candlesticks_response.py
kalshi_python_async/models/bid_ask_distribution.py
kalshi_python_async/models/cancel_order_response.py
kalshi_python_async/models/create_api_key_request.py
kalshi_python_async/models/create_api_key_response.py
kalshi_python_async/models/create_market_in_multivariate_event_collection_request.py
kalshi_python_async-3.4.0.dist-info/METADATA
kalshi_python_async-3.4.0.dist-info/WHEEL
kalshi_python_async-3.4.0.dist-info/top_level.txt
kalshi_python_async-3.4.0.dist-info/RECORD
